pip_services4_data/__init__.py
pip_services4_data/data/IChangeable.py
pip_services4_data/data/IIdentifiable.py
pip_services4_data/data/INamed.py
pip_services4_data/data/IStringIdentifiable.py
pip_services4_data/data/ITrackable.py
pip_services4_data/data/IVersioned.py
pip_services4_data/data/MultiString.py
pip_services4_data/data/__init__.py
pip_services4_data/keys/IdGenerator.py
pip_services4_data/keys/__init__.py
pip_services4_data/process/TagsProcessor.py
pip_services4_data/process/__init__.py
pip_services4_data/query/DataPage.py
pip_services4_data/query/FilterParams.py
pip_services4_data/query/PagingParams.py
pip_services4_data/query/ProjectionParams.py
pip_services4_data/query/SortField.py
pip_services4_data/query/SortParams.py
pip_services4_data/query/TokenizedDataPage.py
pip_services4_data/query/TokenizedPagingParams.py
pip_services4_data/query/__init__.py
pip_services4_data/random/RandomArray.py
pip_services4_data/random/RandomBoolean.py
pip_services4_data/random/RandomDateTime.py
pip_services4_data/random/RandomDouble.py
pip_services4_data/random/RandomFloat.py
pip_services4_data/random/RandomInteger.py
pip_services4_data/random/RandomString.py
pip_services4_data/random/RandomText.py
pip_services4_data/random/__init__.py
pip_services4_data/validate/AndRule.py
pip_services4_data/validate/ArraySchema.py
pip_services4_data/validate/AtLeastOneExistsRule.py
pip_services4_data/validate/ExcludedRule.py
pip_services4_data/validate/FilterParamsSchema.py
pip_services4_data/validate/IValidationRule.py
pip_services4_data/validate/IncludedRule.py
pip_services4_data/validate/MapSchema.py
pip_services4_data/validate/NotRule.py
pip_services4_data/validate/ObjectComparator.py
pip_services4_data/validate/ObjectSchema.py
pip_services4_data/validate/OnlyOneExistRule.py
pip_services4_data/validate/OrRule.py
pip_services4_data/validate/PagingParamsSchema.py
pip_services4_data/validate/ProjectionParamsSchema.py
pip_services4_data/validate/PropertiesComparisonRule.py
pip_services4_data-0.0.4.dist-info/LICENSE
pip_services4_data-0.0.4.dist-info/METADATA
pip_services4_data-0.0.4.dist-info/WHEEL
pip_services4_data-0.0.4.dist-info/top_level.txt
pip_services4_data-0.0.4.dist-info/zip-safe
pip_services4_data-0.0.4.dist-info/RECORD
